AnkiTools/defaults.json
AnkiTools/defaults_api.json
AnkiTools/defaults_formatted.json
AnkiTools/excel/default.xlsx
ankitools/.DS_Store
ankitools/__init__.py
ankitools/_excel.py
ankitools/ankiconnect.py
ankitools/api/__init__.py
ankitools/api/ankidirect.py
ankitools/api/verify.py
ankitools/defaults.json
ankitools/defaults_api.json
ankitools/defaults_formatted.json
ankitools/dir.py
ankitools/editor.py
ankitools/excel/__init__.py
ankitools/excel/app.py
ankitools/excel/default.xlsx
ankitools/excel/formatter.py
ankitools/tools/__init__.py
ankitools/tools/create.py
ankitools/tools/defaults.py
ankitools/tools/guid.py
ankitools/tools/path.py
ankitools/tools/read.py
ankitools/tools/write.py
ankitools-0.3.7.dist-info/LICENSE
ankitools-0.3.7.dist-info/WHEEL
ankitools-0.3.7.dist-info/METADATA
ankitools-0.3.7.dist-info/RECORD
