Metadata-Version: 2.1
Name: ankitools
Version: 0.3.7
Summary: an Anki *.apkg and collection.anki2 reader and editor
Home-page: https://github.com/patarapolw/AnkiTools
Author: Pacharapol Withayasakpunt
Author-email: patarapolw@gmail.com
Keywords: anki,ankiconnect
Requires-Python: >=3.5
Classifier: License :: OSI Approved :: MIT License
Classifier: Programming Language :: Python :: 3
Classifier: Programming Language :: Python :: 3.5
Classifier: Programming Language :: Python :: 3.6
Classifier: Programming Language :: Python :: 3.7
Requires-Dist: appdirs (>=1.4,<2.0)
Requires-Dist: bs4 (>=0.0.1,<0.0.2)
Requires-Dist: openpyxl (>=2.5,<3.0)
Requires-Dist: psutil (>=5.4,<6.0)
Requires-Dist: pyexcel-xlsx (>=0.5.6,<0.6.0)
Requires-Dist: requests (>=2.19,<3.0)
